setup.py
nilan_probability/Binomialdistribution.py
nilan_probability/Gaussiandistribution.py
nilan_probability/Generaldistribution.py
nilan_probability/__init__.py
nilan_probability.egg-info/PKG-INFO
nilan_probability.egg-info/SOURCES.txt
nilan_probability.egg-info/dependency_links.txt
nilan_probability.egg-info/not-zip-safe
nilan_probability.egg-info/top_level.txt