Metadata-Version: 1.0
Name: nilan-probability
Version: 0.1
Summary: Gaussian distributions
Home-page: UNKNOWN
Author: Nilan Fernando
Author-email: michaelnilan@gmail.com
License: UNKNOWN
Platform: UNKNOWN
